{
  "id": "rss-20260512-023",
  "title": "I let AI build a tool to help me figure out what was waking me up at night",
  "source": "rss",
  "source_url": "https://martin.sh/i-let-ai-build-a-tool-to-help-me-figure-out-what-was-waking-me-up-at-night/",
  "author": null,
  "summary": "作者利用AI构建了一个个性化工具，用于分析睡眠数据并找出夜间醒来的原因，展示了AI在日常问题解决中的应用。",
  "highlights": [
    "AI辅助构建睡眠分析工具",
    "个性化数据驱动问题诊断"
  ],
  "tags": [
    "Agent",
    "Tool-use",
    "Data Analysis"
  ],
  "relevance": 6,
  "status": "published",
  "published_at": null,
  "created_at": "2026-05-12T10:21:25Z",
  "updated_at": "2026-05-12T10:21:25Z"
}
